LICENSE
MANIFEST.in
README.rst
setup.cfg
setup.py
django_economy_sectors.egg-info/PKG-INFO
django_economy_sectors.egg-info/SOURCES.txt
django_economy_sectors.egg-info/dependency_links.txt
django_economy_sectors.egg-info/requires.txt
django_economy_sectors.egg-info/top_level.txt
economy_sectors/__init__.py
economy_sectors/apps.py
economy_sectors/utils.py
economy_sectors/fixtures/standards.yaml
economy_sectors/management/__init__.py
economy_sectors/management/commands/__init__.py
economy_sectors/management/commands/load_standards_data.py
economy_sectors/management/commands/load_standards_relations.py
economy_sectors/migrations/0001_initial.py
economy_sectors/migrations/__init__.py
economy_sectors/models/__init__.py
economy_sectors/models/economy_sector.py